Metadata-Version: 2.1
Name: webauth
Version: 0.0.17
Summary: flask auth/oauth wrapper
Home-page: https://github.com/alttch/webauth
Author: Altertech
Author-email: div@altertech.com
License: MIT
Platform: UNKNOWN
Classifier: Programming Language :: Python :: 3
Classifier: License :: OSI Approved :: MIT License
Classifier: Topic :: Software Development :: Libraries
